{
    "GROOVY-10027": {
        "created": "2021-04-09 18:17:47+00:00",
        "resolution": "2021-04-11 15:46:54+00:00",
        "passed": "1 day, 21:29:07",
        "comments": null,
        "reporter": "emilles",
        "assignee": "emilles",
        "reporter_is_assigned": true
    },
    "GROOVY-10011": {
        "created": "2021-04-05 19:48:59+00:00",
        "resolution": "2021-04-10 22:16:23+00:00",
        "passed": "5 days, 2:27:24",
        "comments": null,
        "reporter": "theosot",
        "assignee": "emilles",
        "reporter_is_assigned": false
    },
    "GROOVY-10006": {
        "created": "2021-03-31 16:18:26+00:00",
        "resolution": "2021-04-11 15:47:12+00:00",
        "passed": "10 days, 23:28:46",
        "comments": null,
        "reporter": "knisht",
        "assignee": "emilles",
        "reporter_is_assigned": false
    },
    "GROOVY-9998": {
        "created": "2021-03-23 10:08:42+00:00",
        "resolution": "2021-03-24 12:48:36+00:00",
        "passed": "1 day, 2:39:54",
        "comments": null,
        "reporter": "latanasov",
        "assignee": "emilles",
        "reporter_is_assigned": false
    },
    "GROOVY-9995": {
        "created": "2021-03-22 08:24:14+00:00",
        "resolution": "2021-03-24 14:45:48+00:00",
        "passed": "2 days, 6:21:34",
        "comments": null,
        "reporter": "schaliasos",
        "assignee": "emilles",
        "reporter_is_assigned": false
    },
    "GROOVY-9985": {
        "created": "2021-03-15 10:13:37+00:00",
        "resolution": "2021-03-18 04:17:21+00:00",
        "passed": "2 days, 18:03:44",
        "comments": null,
        "reporter": "theosot",
        "assignee": "paulk",
        "reporter_is_assigned": false
    },
    "GROOVY-9977": {
        "created": "2021-03-10 18:24:25+00:00",
        "resolution": "2021-03-21 18:31:20+00:00",
        "passed": "11 days, 0:06:55",
        "comments": null,
        "reporter": "latanasov",
        "assignee": "emilles",
        "reporter_is_assigned": false
    },
    "GROOVY-9972": {
        "created": "2021-03-08 14:53:09+00:00",
        "resolution": "2021-03-15 13:35:46+00:00",
        "passed": "6 days, 22:42:37",
        "comments": null,
        "reporter": "theosot",
        "assignee": "emilles",
        "reporter_is_assigned": false
    },
    "GROOVY-9970": {
        "created": "2021-03-08 08:31:59+00:00",
        "resolution": "2021-03-15 13:35:26+00:00",
        "passed": "7 days, 5:03:27",
        "comments": null,
        "reporter": "schaliasos",
        "assignee": "emilles",
        "reporter_is_assigned": false
    },
    "GROOVY-9967": {
        "created": "2021-03-05 09:30:07+00:00",
        "resolution": "2021-03-07 02:37:14+00:00",
        "passed": "1 day, 17:07:07",
        "comments": null,
        "reporter": "schaliasos",
        "assignee": "emilles",
        "reporter_is_assigned": false
    },
    "GROOVY-9963": {
        "created": "2021-03-03 21:32:51+00:00",
        "resolution": "2021-03-07 01:34:16+00:00",
        "passed": "3 days, 4:01:25",
        "comments": null,
        "reporter": "theosot",
        "assignee": "emilles",
        "reporter_is_assigned": false
    },
    "GROOVY-9956": {
        "created": "2021-02-26 17:05:46+00:00",
        "resolution": "2021-03-03 00:24:20+00:00",
        "passed": "4 days, 7:18:34",
        "comments": null,
        "reporter": "schaliasos",
        "assignee": "emilles",
        "reporter_is_assigned": false
    },
    "GROOVY-9953": {
        "created": "2021-02-24 18:57:09+00:00",
        "resolution": "2021-03-02 14:58:20+00:00",
        "passed": "5 days, 20:01:11",
        "comments": null,
        "reporter": "schaliasos",
        "assignee": "emilles",
        "reporter_is_assigned": false
    },
    "GROOVY-9948": {
        "created": "2021-02-17 14:17:46+00:00",
        "resolution": "2021-03-02 14:59:59+00:00",
        "passed": "13 days, 0:42:13",
        "comments": null,
        "reporter": "theosot",
        "assignee": "emilles",
        "reporter_is_assigned": false
    },
    "GROOVY-9945": {
        "created": "2021-02-16 07:08:51+00:00",
        "resolution": "2021-03-02 15:00:25+00:00",
        "passed": "14 days, 7:51:34",
        "comments": null,
        "reporter": "schaliasos",
        "assignee": "emilles",
        "reporter_is_assigned": false
    },
    "GROOVY-9935": {
        "created": "2021-02-10 14:00:04+00:00",
        "resolution": "2021-03-02 15:02:49+00:00",
        "passed": "20 days, 1:02:45",
        "comments": null,
        "reporter": "schaliasos",
        "assignee": "emilles",
        "reporter_is_assigned": false
    },
    "GROOVY-9903": {
        "created": "2021-01-20 21:07:33+00:00",
        "resolution": "2021-03-02 15:16:10+00:00",
        "passed": "40 days, 18:08:37",
        "comments": null,
        "reporter": "emilles",
        "assignee": "emilles",
        "reporter_is_assigned": true
    },
    "GROOVY-9891": {
        "created": "2021-01-10 20:18:00+00:00",
        "resolution": "2021-03-02 15:02:15+00:00",
        "passed": "50 days, 18:44:15",
        "comments": null,
        "reporter": "arixmkii",
        "assignee": "emilles",
        "reporter_is_assigned": false
    },
    "GROOVY-9890": {
        "created": "2021-01-10 02:10:15+00:00",
        "resolution": "2021-01-26 12:49:28+00:00",
        "passed": "16 days, 10:39:13",
        "comments": null,
        "reporter": "robinfriedli",
        "assignee": "emilles",
        "reporter_is_assigned": false
    },
    "GROOVY-9885": {
        "created": "2021-01-08 01:47:08+00:00",
        "resolution": "2021-03-02 15:17:11+00:00",
        "passed": "53 days, 13:30:03",
        "comments": null,
        "reporter": "chrylis",
        "assignee": "emilles",
        "reporter_is_assigned": false
    },
    "GROOVY-9882": {
        "created": "2021-01-06 08:15:36+00:00",
        "resolution": "2021-03-02 15:18:06+00:00",
        "passed": "55 days, 7:02:30",
        "comments": null,
        "reporter": "chrylis",
        "assignee": "emilles",
        "reporter_is_assigned": false
    },
    "GROOVY-9881": {
        "created": "2021-01-06 06:36:44+00:00",
        "resolution": "2021-03-02 15:15:32+00:00",
        "passed": "55 days, 8:38:48",
        "comments": null,
        "reporter": "chrylis",
        "assignee": "emilles",
        "reporter_is_assigned": false
    },
    "GROOVY-9844": {
        "created": "2020-12-01 23:06:29+00:00",
        "resolution": "2021-03-31 01:10:14+00:00",
        "passed": "119 days, 2:03:45",
        "comments": null,
        "reporter": "chrylis",
        "assignee": "emilles",
        "reporter_is_assigned": false
    },
    "GROOVY-9821": {
        "created": "2020-11-18 00:00:49+00:00",
        "resolution": "2020-11-20 12:56:49+00:00",
        "passed": "2 days, 12:56:00",
        "comments": null,
        "reporter": "chrylis",
        "assignee": "emilles",
        "reporter_is_assigned": false
    },
    "GROOVY-9803": {
        "created": "2020-10-30 19:30:54+00:00",
        "resolution": "2020-11-14 22:02:54+00:00",
        "passed": "15 days, 2:32:00",
        "comments": null,
        "reporter": "chrylis",
        "assignee": "emilles",
        "reporter_is_assigned": false
    },
    "GROOVY-9763": {
        "created": "2020-09-29 21:51:11+00:00",
        "resolution": "2020-10-09 05:08:57+00:00",
        "passed": "9 days, 7:17:46",
        "comments": null,
        "reporter": "arixmkii",
        "assignee": "emilles",
        "reporter_is_assigned": false
    },
    "GROOVY-9603": {
        "created": "2020-06-20 11:40:15+00:00",
        "resolution": "2020-06-23 04:27:01+00:00",
        "passed": "2 days, 16:46:46",
        "comments": null,
        "reporter": "eddelplus",
        "assignee": "emilles",
        "reporter_is_assigned": false
    },
    "GROOVY-9597": {
        "created": "2020-06-18 13:39:16+00:00",
        "resolution": "2020-07-02 23:44:49+00:00",
        "passed": "14 days, 10:05:33",
        "comments": null,
        "reporter": "fesc",
        "assignee": "emilles",
        "reporter_is_assigned": false
    },
    "GROOVY-9580": {
        "created": "2020-05-31 15:16:16+00:00",
        "resolution": "2020-06-09 12:49:17+00:00",
        "passed": "8 days, 21:33:01",
        "comments": null,
        "reporter": "emilles",
        "assignee": "emilles",
        "reporter_is_assigned": true
    },
    "GROOVY-9518": {
        "created": "2020-04-21 08:29:39+00:00",
        "resolution": "2020-04-23 10:54:25+00:00",
        "passed": "2 days, 2:24:46",
        "comments": null,
        "reporter": "mauromol",
        "assignee": "emilles",
        "reporter_is_assigned": false
    },
    "GROOVY-9463": {
        "created": "2020-03-12 15:30:03+00:00",
        "resolution": "2020-09-22 12:59:05+00:00",
        "passed": "193 days, 21:29:02",
        "comments": null,
        "reporter": "emilles",
        "assignee": "emilles",
        "reporter_is_assigned": true
    },
    "GROOVY-9420": {
        "created": "2020-02-25 08:52:59+00:00",
        "resolution": "2020-02-29 09:10:45+00:00",
        "passed": "4 days, 0:17:46",
        "comments": null,
        "reporter": "mauromol",
        "assignee": "paulk",
        "reporter_is_assigned": false
    },
    "GROOVY-9389": {
        "created": "2020-02-10 16:53:20+00:00",
        "resolution": "2020-02-12 04:42:37+00:00",
        "passed": "1 day, 11:49:17",
        "comments": null,
        "reporter": "bjornvester",
        "assignee": "emilles",
        "reporter_is_assigned": false
    },
    "GROOVY-9370": {
        "created": "2020-01-17 13:28:07+00:00",
        "resolution": "2020-01-22 17:07:26+00:00",
        "passed": "5 days, 3:39:19",
        "comments": null,
        "reporter": "bjornvester",
        "assignee": "emilles",
        "reporter_is_assigned": false
    },
    "GROOVY-9344": {
        "created": "2019-12-19 13:56:21+00:00",
        "resolution": "2020-06-21 23:35:44+00:00",
        "passed": "185 days, 9:39:23",
        "comments": null,
        "reporter": "daniilo",
        "assignee": "emilles",
        "reporter_is_assigned": false
    },
    "GROOVY-9328": {
        "created": "2019-12-04 13:13:56+00:00",
        "resolution": "2019-12-12 01:16:34+00:00",
        "passed": "7 days, 12:02:38",
        "comments": null,
        "reporter": "daniilo",
        "assignee": "emilles",
        "reporter_is_assigned": false
    },
    "GROOVY-9327": {
        "created": "2019-12-04 13:11:06+00:00",
        "resolution": "2019-12-24 00:06:00+00:00",
        "passed": "19 days, 10:54:54",
        "comments": null,
        "reporter": "daniilo",
        "assignee": "emilles",
        "reporter_is_assigned": false
    },
    "GROOVY-9215": {
        "created": "2019-08-08 18:55:24+00:00",
        "resolution": "2019-08-15 07:20:39+00:00",
        "passed": "6 days, 12:25:15",
        "comments": null,
        "reporter": "cinterloper",
        "assignee": "daniel_sun",
        "reporter_is_assigned": false
    },
    "GROOVY-9204": {
        "created": "2019-07-24 12:00:32+00:00",
        "resolution": "2020-02-02 16:55:53+00:00",
        "passed": "193 days, 4:55:21",
        "comments": null,
        "reporter": "daniilo",
        "assignee": "daniel_sun",
        "reporter_is_assigned": false
    },
    "GROOVY-9097": {
        "created": "2019-04-26 15:36:25+00:00",
        "resolution": "2020-03-12 15:22:28+00:00",
        "passed": "320 days, 23:46:03",
        "comments": null,
        "reporter": "emilles",
        "assignee": "",
        "reporter_is_assigned": false
    },
    "GROOVY-8984": {
        "created": "2019-02-08 12:06:24+00:00",
        "resolution": "2021-04-02 16:39:15+00:00",
        "passed": "784 days, 4:32:51",
        "comments": null,
        "reporter": "daniilo",
        "assignee": "emilles",
        "reporter_is_assigned": false
    },
    "GROOVY-8983": {
        "created": "2019-02-08 11:42:31+00:00",
        "resolution": "2021-04-07 13:28:51+00:00",
        "passed": "789 days, 1:46:20",
        "comments": null,
        "reporter": "daniilo",
        "assignee": "emilles",
        "reporter_is_assigned": false
    },
    "GROOVY-8961": {
        "created": "2019-01-18 12:39:34+00:00",
        "resolution": "2020-09-20 01:05:45+00:00",
        "passed": "610 days, 12:26:11",
        "comments": null,
        "reporter": "daniilo",
        "assignee": "emilles",
        "reporter_is_assigned": false
    },
    "GROOVY-8909": {
        "created": "2018-12-05 11:33:46+00:00",
        "resolution": "2021-03-31 01:10:01+00:00",
        "passed": "846 days, 13:36:15",
        "comments": null,
        "reporter": "daniilo",
        "assignee": "emilles",
        "reporter_is_assigned": false
    },
    "GROOVY-8686": {
        "created": "2018-07-05 23:07:46+00:00",
        "resolution": "2019-11-21 08:48:27+00:00",
        "passed": "503 days, 9:40:41",
        "comments": null,
        "reporter": "emilles",
        "assignee": "emilles",
        "reporter_is_assigned": true
    },
    "GROOVY-8629": {
        "created": "2018-06-04 06:20:23+00:00",
        "resolution": "2018-06-05 01:54:26+00:00",
        "passed": "19:34:03",
        "comments": null,
        "reporter": "msgilligan",
        "assignee": "daniel_sun",
        "reporter_is_assigned": false
    },
    "GROOVY-8613": {
        "created": "2018-05-28 15:40:28+00:00",
        "resolution": "2018-06-01 18:08:40+00:00",
        "passed": "4 days, 2:28:12",
        "comments": null,
        "reporter": "daniilo",
        "assignee": "daniel_sun",
        "reporter_is_assigned": false
    },
    "GROOVY-8610": {
        "created": "2018-05-27 19:06:26+00:00",
        "resolution": "2018-05-28 10:44:48+00:00",
        "passed": "15:38:22",
        "comments": null,
        "reporter": "jwagenleitner",
        "assignee": "jwagenleitner",
        "reporter_is_assigned": true
    },
    "GROOVY-8609": {
        "created": "2018-05-27 11:33:01+00:00",
        "resolution": "2018-05-28 12:38:03+00:00",
        "passed": "1 day, 1:05:02",
        "comments": null,
        "reporter": "daniel_sun",
        "assignee": "daniel_sun",
        "reporter_is_assigned": true
    },
    "GROOVY-8590": {
        "created": "2018-05-20 04:15:44+00:00",
        "resolution": "2018-05-23 01:25:05+00:00",
        "passed": "2 days, 21:09:21",
        "comments": null,
        "reporter": "jwagenleitner",
        "assignee": "jwagenleitner",
        "reporter_is_assigned": true
    },
    "GROOVY-8583": {
        "created": "2018-05-14 11:09:02+00:00",
        "resolution": "2018-06-06 01:40:20+00:00",
        "passed": "22 days, 14:31:18",
        "comments": null,
        "reporter": "daniel_sun",
        "assignee": "jwagenleitner",
        "reporter_is_assigned": false
    },
    "GROOVY-8572": {
        "created": "2018-05-07 13:19:19+00:00",
        "resolution": "2019-10-29 16:58:43+00:00",
        "passed": "540 days, 3:39:24",
        "comments": null,
        "reporter": "skurla.martin@gmail.com",
        "assignee": "emilles",
        "reporter_is_assigned": false
    },
    "GROOVY-8523": {
        "created": "2018-03-28 19:11:49+00:00",
        "resolution": "2018-04-03 05:34:42+00:00",
        "passed": "5 days, 10:22:53",
        "comments": null,
        "reporter": "Nikolas",
        "assignee": "paulk",
        "reporter_is_assigned": false
    },
    "GROOVY-8445": {
        "created": "2018-01-12 15:10:43+00:00",
        "resolution": "2018-02-02 10:08:47+00:00",
        "passed": "20 days, 18:58:04",
        "comments": null,
        "reporter": "daniel_sun",
        "assignee": "daniel_sun",
        "reporter_is_assigned": true
    },
    "GROOVY-8394": {
        "created": "2017-11-27 10:30:54+00:00",
        "resolution": "2019-10-29 18:40:40+00:00",
        "passed": "701 days, 8:09:46",
        "comments": null,
        "reporter": "daniilo",
        "assignee": "",
        "reporter_is_assigned": false
    },
    "GROOVY-8389": {
        "created": "2017-11-24 18:58:20+00:00",
        "resolution": "2018-06-29 19:47:31+00:00",
        "passed": "217 days, 0:49:11",
        "comments": null,
        "reporter": "daniilo",
        "assignee": "daniel_sun",
        "reporter_is_assigned": false
    },
    "GROOVY-8337": {
        "created": "2017-10-02 01:00:28+00:00",
        "resolution": "2018-08-26 02:08:35+00:00",
        "passed": "328 days, 1:08:07",
        "comments": null,
        "reporter": "emilles",
        "assignee": "daniel_sun",
        "reporter_is_assigned": false
    },
    "GROOVY-8330": {
        "created": "2017-09-26 14:24:29+00:00",
        "resolution": "2017-09-27 07:00:21+00:00",
        "passed": "16:35:52",
        "comments": null,
        "reporter": "Alexey Afanasiev",
        "assignee": "daniel_sun",
        "reporter_is_assigned": false
    },
    "GROOVY-8321": {
        "created": "2017-09-16 04:02:05+00:00",
        "resolution": "2019-10-29 19:07:34+00:00",
        "passed": "773 days, 15:05:29",
        "comments": null,
        "reporter": "paulk",
        "assignee": "",
        "reporter_is_assigned": false
    },
    "GROOVY-8319": {
        "created": "2017-09-15 14:12:20+00:00",
        "resolution": "2017-09-15 16:34:06+00:00",
        "passed": "2:21:46",
        "comments": null,
        "reporter": "Alexey Afanasiev",
        "assignee": "daniel_sun",
        "reporter_is_assigned": false
    },
    "GROOVY-8317": {
        "created": "2017-09-13 13:21:16+00:00",
        "resolution": "2017-12-13 04:55:11+00:00",
        "passed": "90 days, 15:33:55",
        "comments": null,
        "reporter": "Alexey Afanasiev",
        "assignee": "daniel_sun",
        "reporter_is_assigned": false
    },
    "GROOVY-8310": {
        "created": "2017-09-07 16:14:50+00:00",
        "resolution": "2019-11-15 03:08:11+00:00",
        "passed": "798 days, 10:53:21",
        "comments": null,
        "reporter": "Alexey Afanasiev",
        "assignee": "emilles",
        "reporter_is_assigned": false
    },
    "GROOVY-8255": {
        "created": "2017-07-14 10:35:22+00:00",
        "resolution": "2017-11-14 13:44:12+00:00",
        "passed": "123 days, 3:08:50",
        "comments": null,
        "reporter": "graemerocher1",
        "assignee": "paulk",
        "reporter_is_assigned": false
    },
    "GROOVY-8247": {
        "created": "2017-07-04 10:36:52+00:00",
        "resolution": "2017-09-14 10:24:22+00:00",
        "passed": "71 days, 23:47:30",
        "comments": null,
        "reporter": "daniilo",
        "assignee": "paulk",
        "reporter_is_assigned": false
    },
    "GROOVY-8246": {
        "created": "2017-07-04 10:33:56+00:00",
        "resolution": "2017-09-14 10:24:42+00:00",
        "passed": "71 days, 23:50:46",
        "comments": null,
        "reporter": "daniilo",
        "assignee": "paulk",
        "reporter_is_assigned": false
    },
    "GROOVY-8241": {
        "created": "2017-06-30 13:14:35+00:00",
        "resolution": "2017-12-13 04:56:39+00:00",
        "passed": "165 days, 15:42:04",
        "comments": null,
        "reporter": "daniilo",
        "assignee": "daniel_sun",
        "reporter_is_assigned": false
    },
    "GROOVY-8205": {
        "created": "2017-05-25 10:04:35+00:00",
        "resolution": "2017-08-26 19:36:05+00:00",
        "passed": "93 days, 9:31:30",
        "comments": null,
        "reporter": "ichulovskyi",
        "assignee": "jwagenleitner",
        "reporter_is_assigned": false
    },
    "GROOVY-8195": {
        "created": "2017-05-21 09:02:47+00:00",
        "resolution": "2018-06-17 03:08:37+00:00",
        "passed": "391 days, 18:05:50",
        "comments": null,
        "reporter": "pootow",
        "assignee": "jwagenleitner",
        "reporter_is_assigned": false
    },
    "GROOVY-8157": {
        "created": "2017-04-13 12:33:25+00:00",
        "resolution": "2017-05-11 15:49:40+00:00",
        "passed": "28 days, 3:16:15",
        "comments": null,
        "reporter": "daniilo",
        "assignee": "shils",
        "reporter_is_assigned": false
    },
    "GROOVY-8103": {
        "created": "2017-03-01 17:04:50+00:00",
        "resolution": "2020-09-17 22:38:38+00:00",
        "passed": "1296 days, 5:33:48",
        "comments": null,
        "reporter": "emilles",
        "assignee": "",
        "reporter_is_assigned": false
    },
    "GROOVY-8090": {
        "created": "2017-02-20 04:36:58+00:00",
        "resolution": "2018-08-26 08:37:46+00:00",
        "passed": "552 days, 4:00:48",
        "comments": null,
        "reporter": "paulk",
        "assignee": "daniel_sun",
        "reporter_is_assigned": false
    },
    "GROOVY-8084": {
        "created": "2017-02-08 10:06:59+00:00",
        "resolution": "2018-08-24 19:57:03+00:00",
        "passed": "562 days, 9:50:04",
        "comments": null,
        "reporter": "Alexey Afanasiev",
        "assignee": "daniel_sun",
        "reporter_is_assigned": false
    },
    "GROOVY-8059": {
        "created": "2017-01-22 06:39:51+00:00",
        "resolution": "2018-05-11 06:47:20+00:00",
        "passed": "474 days, 0:07:29",
        "comments": null,
        "reporter": "jwagenleitner",
        "assignee": "daniel_sun",
        "reporter_is_assigned": false
    },
    "GROOVY-8034": {
        "created": "2017-01-04 23:34:40+00:00",
        "resolution": "2021-03-26 15:39:18+00:00",
        "passed": "1541 days, 16:04:38",
        "comments": null,
        "reporter": "uze@yandex.ru",
        "assignee": "emilles",
        "reporter_is_assigned": false
    },
    "GROOVY-8033": {
        "created": "2017-01-03 21:14:22+00:00",
        "resolution": "2017-01-10 00:00:30+00:00",
        "passed": "6 days, 2:46:08",
        "comments": null,
        "reporter": "emilles",
        "assignee": "shils",
        "reporter_is_assigned": false
    },
    "GROOVY-8001": {
        "created": "2016-11-18 19:52:04+00:00",
        "resolution": "2021-04-02 14:38:27+00:00",
        "passed": "1595 days, 18:46:23",
        "comments": null,
        "reporter": "jmsotuyo",
        "assignee": "emilles",
        "reporter_is_assigned": false
    },
    "GROOVY-7987": {
        "created": "2016-11-02 01:27:17+00:00",
        "resolution": "2016-11-06 23:42:28+00:00",
        "passed": "4 days, 22:15:11",
        "comments": null,
        "reporter": "paulk",
        "assignee": "paulk",
        "reporter_is_assigned": true
    },
    "GROOVY-7985": {
        "created": "2016-10-31 16:49:54+00:00",
        "resolution": "2018-05-11 06:12:14+00:00",
        "passed": "556 days, 13:22:20",
        "comments": null,
        "reporter": "mauromol",
        "assignee": "daniel_sun",
        "reporter_is_assigned": false
    },
    "GROOVY-7953": {
        "created": "2016-10-04 01:14:19+00:00",
        "resolution": "2016-10-09 17:03:54+00:00",
        "passed": "5 days, 15:49:35",
        "comments": null,
        "reporter": "shils",
        "assignee": "shils",
        "reporter_is_assigned": true
    },
    "GROOVY-7952": {
        "created": "2016-10-04 01:02:54+00:00",
        "resolution": "2016-10-06 03:06:13+00:00",
        "passed": "2 days, 2:03:19",
        "comments": null,
        "reporter": "shils",
        "assignee": "shils",
        "reporter_is_assigned": true
    },
    "GROOVY-7929": {
        "created": "2016-09-05 12:30:25+00:00",
        "resolution": "2018-01-25 03:28:35+00:00",
        "passed": "506 days, 14:58:10",
        "comments": null,
        "reporter": "daniilo",
        "assignee": "paulk",
        "reporter_is_assigned": false
    },
    "GROOVY-7922": {
        "created": "2016-08-29 13:05:30+00:00",
        "resolution": "2016-09-20 03:32:21+00:00",
        "passed": "21 days, 14:26:51",
        "comments": null,
        "reporter": "paulk",
        "assignee": "jwagenleitner",
        "reporter_is_assigned": false
    },
    "GROOVY-7888": {
        "created": "2016-07-20 10:51:19+00:00",
        "resolution": "2016-08-24 07:40:53+00:00",
        "passed": "34 days, 20:49:34",
        "comments": null,
        "reporter": "wolfs",
        "assignee": "paulk",
        "reporter_is_assigned": false
    },
    "GROOVY-7880": {
        "created": "2016-07-05 16:23:30+00:00",
        "resolution": "2016-08-11 09:08:45+00:00",
        "passed": "36 days, 16:45:15",
        "comments": null,
        "reporter": "leuprechtroman",
        "assignee": "paulk",
        "reporter_is_assigned": false
    },
    "GROOVY-7813": {
        "created": "2016-04-09 19:48:48+00:00",
        "resolution": "2016-05-26 15:07:41+00:00",
        "passed": "46 days, 19:18:53",
        "comments": null,
        "reporter": "shils",
        "assignee": "shils",
        "reporter_is_assigned": true
    },
    "GROOVY-7753": {
        "created": "2016-02-10 20:46:32+00:00",
        "resolution": "2018-05-14 10:57:55+00:00",
        "passed": "823 days, 14:11:23",
        "comments": null,
        "reporter": "gillius",
        "assignee": "daniel_sun",
        "reporter_is_assigned": false
    },
    "GROOVY-7748": {
        "created": "2016-02-04 08:33:22+00:00",
        "resolution": "2017-01-08 19:48:45+00:00",
        "passed": "339 days, 11:15:23",
        "comments": null,
        "reporter": "maxim.medvedev",
        "assignee": "",
        "reporter_is_assigned": false
    },
    "GROOVY-7721": {
        "created": "2015-12-28 14:25:03+00:00",
        "resolution": "2017-09-13 15:09:14+00:00",
        "passed": "625 days, 0:44:11",
        "comments": null,
        "reporter": "gromopetr",
        "assignee": "daniel_sun",
        "reporter_is_assigned": false
    },
    "GROOVY-7717": {
        "created": "2015-12-21 03:49:11+00:00",
        "resolution": "2015-12-21 13:51:03+00:00",
        "passed": "10:01:52",
        "comments": null,
        "reporter": "shils",
        "assignee": "shils",
        "reporter_is_assigned": true
    },
    "GROOVY-7713": {
        "created": "2015-12-17 22:51:27+00:00",
        "resolution": "2016-08-19 02:38:30+00:00",
        "passed": "245 days, 3:47:03",
        "comments": null,
        "reporter": "uberska",
        "assignee": "jwagenleitner",
        "reporter_is_assigned": false
    },
    "GROOVY-7711": {
        "created": "2015-12-14 21:48:43+00:00",
        "resolution": "2015-12-28 07:04:07+00:00",
        "passed": "13 days, 9:15:24",
        "comments": null,
        "reporter": "fpavageau",
        "assignee": "pascalschumacher",
        "reporter_is_assigned": false
    },
    "GROOVY-7710": {
        "created": "2015-12-14 21:37:08+00:00",
        "resolution": "2015-12-28 07:03:30+00:00",
        "passed": "13 days, 9:26:22",
        "comments": null,
        "reporter": "fpavageau",
        "assignee": "pascalschumacher",
        "reporter_is_assigned": false
    },
    "GROOVY-7691": {
        "created": "2015-11-26 22:27:56+00:00",
        "resolution": "2018-05-13 13:18:26+00:00",
        "passed": "898 days, 14:50:30",
        "comments": null,
        "reporter": "fpavageau",
        "assignee": "daniel_sun",
        "reporter_is_assigned": false
    },
    "GROOVY-7627": {
        "created": "2015-10-13 05:03:49+00:00",
        "resolution": "2016-01-26 05:25:52+00:00",
        "passed": "105 days, 0:22:03",
        "comments": null,
        "reporter": "shils",
        "assignee": "shils",
        "reporter_is_assigned": true
    },
    "GROOVY-7618": {
        "created": "2015-10-07 04:19:27+00:00",
        "resolution": "2015-10-07 19:24:03+00:00",
        "passed": "15:04:36",
        "comments": null,
        "reporter": "shils",
        "assignee": "melix",
        "reporter_is_assigned": false
    },
    "GROOVY-7598": {
        "created": "2015-09-22 16:24:58+00:00",
        "resolution": "2015-10-07 19:23:42+00:00",
        "passed": "15 days, 2:58:44",
        "comments": null,
        "reporter": "jechlin",
        "assignee": "melix",
        "reporter_is_assigned": false
    },
    "GROOVY-7597": {
        "created": "2015-09-21 18:54:11+00:00",
        "resolution": "2015-10-07 19:23:13+00:00",
        "passed": "16 days, 0:29:02",
        "comments": null,
        "reporter": "gillius",
        "assignee": "melix",
        "reporter_is_assigned": false
    },
    "GROOVY-7538": {
        "created": "2015-08-01 21:35:03+00:00",
        "resolution": "2015-11-28 20:00:16+00:00",
        "passed": "118 days, 22:25:13",
        "comments": null,
        "reporter": "fpavageau",
        "assignee": "pascalschumacher",
        "reporter_is_assigned": false
    },
    "GROOVY-7512": {
        "created": "2015-07-20 14:30:21+00:00",
        "resolution": "2020-06-13 13:29:23+00:00",
        "passed": "1789 days, 22:59:02",
        "comments": null,
        "reporter": "cesarizu",
        "assignee": "emilles",
        "reporter_is_assigned": false
    },
    "GROOVY-7434": {
        "created": "2015-05-25 09:54:34+00:00",
        "resolution": "2015-05-26 12:10:38+00:00",
        "passed": "1 day, 2:16:04",
        "comments": null,
        "reporter": "paulk",
        "assignee": "paulk",
        "reporter_is_assigned": true
    },
    "GROOVY-7420": {
        "created": "2015-05-10 21:52:04+00:00",
        "resolution": "2015-12-16 21:55:41+00:00",
        "passed": "220 days, 0:03:37",
        "comments": null,
        "reporter": "fpavageau",
        "assignee": "pascalschumacher",
        "reporter_is_assigned": false
    },
    "GROOVY-7419": {
        "created": "2015-05-08 19:58:00+00:00",
        "resolution": "2021-03-18 13:54:14+00:00",
        "passed": "2140 days, 17:56:14",
        "comments": null,
        "reporter": "dsheehan",
        "assignee": "emilles",
        "reporter_is_assigned": false
    },
    "GROOVY-7365": {
        "created": "2015-03-23 17:31:10+00:00",
        "resolution": "2015-03-25 07:55:20+00:00",
        "passed": "1 day, 14:24:10",
        "comments": null,
        "reporter": "fpavageau",
        "assignee": "melix",
        "reporter_is_assigned": false
    },
    "GROOVY-7364": {
        "created": "2015-03-23 06:07:37+00:00",
        "resolution": "2015-03-23 06:44:17+00:00",
        "passed": "0:36:40",
        "comments": null,
        "reporter": "fpavageau",
        "assignee": "melix",
        "reporter_is_assigned": false
    },
    "GROOVY-7363": {
        "created": "2015-03-23 05:35:47+00:00",
        "resolution": "2015-11-03 18:07:35+00:00",
        "passed": "225 days, 12:31:48",
        "comments": null,
        "reporter": "fpavageau",
        "assignee": "pascalschumacher",
        "reporter_is_assigned": false
    },
    "GROOVY-7333": {
        "created": "2015-03-09 06:12:54+00:00",
        "resolution": "2015-03-09 08:16:10+00:00",
        "passed": "2:03:16",
        "comments": null,
        "reporter": "melix",
        "assignee": "melix",
        "reporter_is_assigned": true
    },
    "GROOVY-7327": {
        "created": "2015-03-02 10:16:59+00:00",
        "resolution": "2015-03-06 09:04:28+00:00",
        "passed": "3 days, 22:47:29",
        "comments": null,
        "reporter": "tkruse",
        "assignee": "melix",
        "reporter_is_assigned": false
    },
    "GROOVY-7316": {
        "created": "2015-02-20 15:38:46+00:00",
        "resolution": "2015-03-20 08:59:05+00:00",
        "passed": "27 days, 17:20:19",
        "comments": null,
        "reporter": "gillius",
        "assignee": "melix",
        "reporter_is_assigned": false
    },
    "GROOVY-7315": {
        "created": "2015-02-20 15:34:49+00:00",
        "resolution": "2017-11-13 02:53:10+00:00",
        "passed": "996 days, 11:18:21",
        "comments": null,
        "reporter": "gillius",
        "assignee": "paulk",
        "reporter_is_assigned": false
    },
    "GROOVY-7307": {
        "created": "2015-02-18 07:16:04+00:00",
        "resolution": "2015-03-20 07:17:49+00:00",
        "passed": "30 days, 0:01:45",
        "comments": null,
        "reporter": "fpavageau",
        "assignee": "melix",
        "reporter_is_assigned": false
    },
    "GROOVY-7211": {
        "created": "2014-12-16 21:19:22+00:00",
        "resolution": "2015-03-02 05:20:50+00:00",
        "passed": "75 days, 8:01:28",
        "comments": null,
        "reporter": "druid0523",
        "assignee": "melix",
        "reporter_is_assigned": false
    },
    "GROOVY-7210": {
        "created": "2014-12-16 09:38:47+00:00",
        "resolution": "2014-12-16 10:24:09+00:00",
        "passed": "0:45:22",
        "comments": null,
        "reporter": "blackdrag",
        "assignee": "melix",
        "reporter_is_assigned": false
    },
    "GROOVY-7204": {
        "created": "2014-12-10 02:48:13+00:00",
        "resolution": "2018-05-10 08:02:18+00:00",
        "passed": "1247 days, 5:14:05",
        "comments": null,
        "reporter": "mauromol",
        "assignee": "daniel_sun",
        "reporter_is_assigned": false
    },
    "GROOVY-7170": {
        "created": "2014-11-15 15:26:05+00:00",
        "resolution": "2015-11-15 10:34:13+00:00",
        "passed": "364 days, 19:08:08",
        "comments": null,
        "reporter": "uehaj",
        "assignee": "pascalschumacher",
        "reporter_is_assigned": false
    },
    "GROOVY-7159": {
        "created": "2014-11-08 08:25:05+00:00",
        "resolution": "2015-05-07 20:52:14+00:00",
        "passed": "180 days, 12:27:09",
        "comments": null,
        "reporter": "uehaj",
        "assignee": "melix",
        "reporter_is_assigned": false
    },
    "GROOVY-7145": {
        "created": "2014-11-03 06:55:48+00:00",
        "resolution": "2014-11-04 07:16:19+00:00",
        "passed": "1 day, 0:20:31",
        "comments": null,
        "reporter": "jespersm",
        "assignee": "melix",
        "reporter_is_assigned": false
    },
    "GROOVY-7128": {
        "created": "2014-10-24 08:04:11+00:00",
        "resolution": "2021-03-28 18:39:06+00:00",
        "passed": "2347 days, 10:34:55",
        "comments": null,
        "reporter": "yukoba",
        "assignee": "emilles",
        "reporter_is_assigned": false
    },
    "GROOVY-7122": {
        "created": "2014-10-18 06:04:14+00:00",
        "resolution": "2014-10-22 13:35:54+00:00",
        "passed": "4 days, 7:31:40",
        "comments": null,
        "reporter": "yukoba",
        "assignee": "blackdrag",
        "reporter_is_assigned": false
    },
    "GROOVY-7061": {
        "created": "2014-09-08 11:09:11+00:00",
        "resolution": "2017-12-13 04:55:59+00:00",
        "passed": "1191 days, 17:46:48",
        "comments": null,
        "reporter": "pledbrook",
        "assignee": "daniel_sun",
        "reporter_is_assigned": false
    },
    "GROOVY-7035": {
        "created": "2014-08-22 03:29:55+00:00",
        "resolution": "2014-08-22 03:49:21+00:00",
        "passed": "0:19:26",
        "comments": null,
        "reporter": "bsideup",
        "assignee": "melix",
        "reporter_is_assigned": false
    },
    "GROOVY-7021": {
        "created": "2014-08-12 13:10:19+00:00",
        "resolution": "2014-12-28 10:52:15+00:00",
        "passed": "137 days, 21:41:56",
        "comments": null,
        "reporter": "ilbmiller",
        "assignee": "",
        "reporter_is_assigned": false
    },
    "GROOVY-7015": {
        "created": "2014-08-08 08:46:02+00:00",
        "resolution": "2014-11-13 09:00:54+00:00",
        "passed": "97 days, 0:14:52",
        "comments": null,
        "reporter": "harminder",
        "assignee": "blackdrag",
        "reporter_is_assigned": false
    },
    "GROOVY-6970": {
        "created": "2014-07-23 09:25:26+00:00",
        "resolution": "2014-07-23 11:10:36+00:00",
        "passed": "1:45:10",
        "comments": null,
        "reporter": "tachatte",
        "assignee": "melix",
        "reporter_is_assigned": false
    },
    "GROOVY-6961": {
        "created": "2014-07-19 12:33:11+00:00",
        "resolution": "2014-07-22 06:54:34+00:00",
        "passed": "2 days, 18:21:23",
        "comments": null,
        "reporter": "robfletcher",
        "assignee": "blackdrag",
        "reporter_is_assigned": false
    },
    "GROOVY-6912": {
        "created": "2014-07-04 02:39:01+00:00",
        "resolution": "2021-03-28 18:39:54+00:00",
        "passed": "2459 days, 16:00:53",
        "comments": null,
        "reporter": "paulk",
        "assignee": "emilles",
        "reporter_is_assigned": false
    },
    "GROOVY-6904": {
        "created": "2014-07-02 11:47:58+00:00",
        "resolution": "2014-07-03 04:23:14+00:00",
        "passed": "16:35:16",
        "comments": null,
        "reporter": "blackdrag",
        "assignee": "blackdrag",
        "reporter_is_assigned": true
    },
    "GROOVY-6888": {
        "created": "2014-06-20 17:25:50+00:00",
        "resolution": "2018-02-01 06:23:58+00:00",
        "passed": "1321 days, 12:58:08",
        "comments": null,
        "reporter": "mauromol",
        "assignee": "paulk",
        "reporter_is_assigned": false
    },
    "GROOVY-6835": {
        "created": "2014-05-29 02:49:06+00:00",
        "resolution": "2016-01-05 03:14:17+00:00",
        "passed": "586 days, 0:25:11",
        "comments": null,
        "reporter": "lhotari",
        "assignee": "paulk",
        "reporter_is_assigned": false
    },
    "GROOVY-6806": {
        "created": "2014-05-19 12:02:05+00:00",
        "resolution": "2014-05-19 12:07:22+00:00",
        "passed": "0:05:17",
        "comments": null,
        "reporter": "melix",
        "assignee": "melix",
        "reporter_is_assigned": true
    },
    "GROOVY-6804": {
        "created": "2014-05-19 10:14:21+00:00",
        "resolution": "2014-06-11 07:37:44+00:00",
        "passed": "22 days, 21:23:23",
        "comments": null,
        "reporter": "bsideup",
        "assignee": "melix",
        "reporter_is_assigned": false
    },
    "GROOVY-6800": {
        "created": "2014-05-19 03:39:47+00:00",
        "resolution": "2015-12-14 18:07:19+00:00",
        "passed": "574 days, 14:27:32",
        "comments": null,
        "reporter": "robfletcher",
        "assignee": "melix",
        "reporter_is_assigned": false
    },
    "GROOVY-6791": {
        "created": "2014-05-14 14:45:18+00:00",
        "resolution": "2014-10-23 14:09:49+00:00",
        "passed": "161 days, 23:24:31",
        "comments": null,
        "reporter": "yukoba",
        "assignee": "blackdrag",
        "reporter_is_assigned": false
    },
    "GROOVY-6787": {
        "created": "2014-05-13 09:48:24+00:00",
        "resolution": "2015-12-23 08:59:03+00:00",
        "passed": "588 days, 23:10:39",
        "comments": null,
        "reporter": "blackdrag",
        "assignee": "pascalschumacher",
        "reporter_is_assigned": false
    },
    "GROOVY-6786": {
        "created": "2014-05-12 17:00:41+00:00",
        "resolution": "2014-05-15 09:38:46+00:00",
        "passed": "2 days, 16:38:05",
        "comments": null,
        "reporter": "bsideup",
        "assignee": "blackdrag",
        "reporter_is_assigned": false
    },
    "GROOVY-6781": {
        "created": "2014-05-11 13:00:04+00:00",
        "resolution": "2015-03-13 14:35:14+00:00",
        "passed": "306 days, 1:35:10",
        "comments": null,
        "reporter": "pniederw",
        "assignee": "melix",
        "reporter_is_assigned": false
    },
    "GROOVY-6776": {
        "created": "2014-05-09 06:28:25+00:00",
        "resolution": "2014-05-09 09:37:45+00:00",
        "passed": "3:09:20",
        "comments": null,
        "reporter": "graemerocher",
        "assignee": "blackdrag",
        "reporter_is_assigned": false
    },
    "GROOVY-6761": {
        "created": "2014-05-06 03:33:18+00:00",
        "resolution": "2014-05-14 09:43:44+00:00",
        "passed": "8 days, 6:10:26",
        "comments": null,
        "reporter": "ldaley",
        "assignee": "blackdrag",
        "reporter_is_assigned": false
    },
    "GROOVY-6760": {
        "created": "2014-05-06 02:46:31+00:00",
        "resolution": "2014-05-08 10:18:18+00:00",
        "passed": "2 days, 7:31:47",
        "comments": null,
        "reporter": "ldaley",
        "assignee": "blackdrag",
        "reporter_is_assigned": false
    },
    "GROOVY-6757": {
        "created": "2014-05-06 01:04:09+00:00",
        "resolution": "2015-03-20 08:18:55+00:00",
        "passed": "318 days, 7:14:46",
        "comments": null,
        "reporter": "ldaley",
        "assignee": "melix",
        "reporter_is_assigned": false
    },
    "GROOVY-6751": {
        "created": "2014-05-02 14:53:53+00:00",
        "resolution": "2014-05-15 14:30:36+00:00",
        "passed": "12 days, 23:36:43",
        "comments": null,
        "reporter": "ngalarneau",
        "assignee": "",
        "reporter_is_assigned": false
    },
    "GROOVY-6748": {
        "created": "2014-05-02 05:09:34+00:00",
        "resolution": "2014-05-12 08:50:00+00:00",
        "passed": "10 days, 3:40:26",
        "comments": null,
        "reporter": "mperry",
        "assignee": "blackdrag",
        "reporter_is_assigned": false
    },
    "GROOVY-6742": {
        "created": "2014-04-30 08:00:58+00:00",
        "resolution": "2018-05-11 09:56:12+00:00",
        "passed": "1472 days, 1:55:14",
        "comments": null,
        "reporter": "nithril",
        "assignee": "daniel_sun",
        "reporter_is_assigned": false
    },
    "GROOVY-6738": {
        "created": "2014-04-29 08:14:50+00:00",
        "resolution": "2016-11-07 18:05:54+00:00",
        "passed": "923 days, 9:51:04",
        "comments": null,
        "reporter": "pniederw",
        "assignee": "shils",
        "reporter_is_assigned": false
    },
    "GROOVY-6731": {
        "created": "2014-04-27 12:18:21+00:00",
        "resolution": "2014-05-15 04:32:22+00:00",
        "passed": "17 days, 16:14:01",
        "comments": null,
        "reporter": "nithril",
        "assignee": "melix",
        "reporter_is_assigned": false
    },
    "GROOVY-6730": {
        "created": "2014-04-27 12:12:14+00:00",
        "resolution": "2014-05-15 04:34:46+00:00",
        "passed": "17 days, 16:22:32",
        "comments": null,
        "reporter": "nithril",
        "assignee": "melix",
        "reporter_is_assigned": false
    },
    "GROOVY-6723": {
        "created": "2014-04-25 05:51:53+00:00",
        "resolution": "2014-04-30 13:52:48+00:00",
        "passed": "5 days, 8:00:55",
        "comments": null,
        "reporter": "mperry",
        "assignee": "blackdrag",
        "reporter_is_assigned": false
    },
    "GROOVY-6693": {
        "created": "2014-04-10 10:40:32+00:00",
        "resolution": "2014-05-12 05:15:03+00:00",
        "passed": "31 days, 18:34:31",
        "comments": null,
        "reporter": "melix",
        "assignee": "blackdrag",
        "reporter_is_assigned": false
    },
    "GROOVY-6676": {
        "created": "2014-04-07 08:46:31+00:00",
        "resolution": "2014-04-07 08:47:44+00:00",
        "passed": "0:01:13",
        "comments": null,
        "reporter": "melix",
        "assignee": "melix",
        "reporter_is_assigned": true
    },
    "GROOVY-6671": {
        "created": "2014-04-04 20:42:52+00:00",
        "resolution": "2014-05-06 02:45:39+00:00",
        "passed": "31 days, 6:02:47",
        "comments": null,
        "reporter": "ldaley",
        "assignee": "blackdrag",
        "reporter_is_assigned": false
    },
    "GROOVY-6659": {
        "created": "2014-04-04 02:22:52+00:00",
        "resolution": "2016-09-30 00:59:15+00:00",
        "passed": "909 days, 22:36:23",
        "comments": null,
        "reporter": "blackdrag",
        "assignee": "",
        "reporter_is_assigned": false
    },
    "GROOVY-6657": {
        "created": "2014-04-03 12:36:29+00:00",
        "resolution": "2014-04-03 15:44:22+00:00",
        "passed": "3:07:53",
        "comments": null,
        "reporter": "melix",
        "assignee": "melix",
        "reporter_is_assigned": true
    },
    "GROOVY-6636": {
        "created": "2014-03-26 06:36:18+00:00",
        "resolution": "2014-09-19 07:15:01+00:00",
        "passed": "177 days, 0:38:43",
        "comments": null,
        "reporter": "lhotari",
        "assignee": "melix",
        "reporter_is_assigned": false
    },
    "GROOVY-6614": {
        "created": "2014-03-07 15:06:10+00:00",
        "resolution": "2014-06-20 20:49:18+00:00",
        "passed": "105 days, 5:43:08",
        "comments": null,
        "reporter": "sean.true",
        "assignee": "paulk",
        "reporter_is_assigned": false
    },
    "GROOVY-6601": {
        "created": "2014-02-26 23:52:16+00:00",
        "resolution": "2014-05-07 03:45:12+00:00",
        "passed": "69 days, 3:52:56",
        "comments": null,
        "reporter": "ddimitrov",
        "assignee": "melix",
        "reporter_is_assigned": false
    },
    "GROOVY-6590": {
        "created": "2014-02-20 04:49:22+00:00",
        "resolution": "2015-01-14 06:53:28+00:00",
        "passed": "328 days, 2:04:06",
        "comments": null,
        "reporter": "blackdrag",
        "assignee": "melix",
        "reporter_is_assigned": false
    },
    "GROOVY-6577": {
        "created": "2014-02-14 09:39:21+00:00",
        "resolution": "2014-02-17 06:05:12+00:00",
        "passed": "2 days, 20:25:51",
        "comments": null,
        "reporter": "blackdrag",
        "assignee": "melix",
        "reporter_is_assigned": false
    },
    "GROOVY-6575": {
        "created": "2014-02-14 09:09:35+00:00",
        "resolution": "2014-02-17 04:22:53+00:00",
        "passed": "2 days, 19:13:18",
        "comments": null,
        "reporter": "blackdrag",
        "assignee": "melix",
        "reporter_is_assigned": false
    },
    "GROOVY-6528": {
        "created": "2014-01-20 09:34:23+00:00",
        "resolution": "2014-02-17 07:49:14+00:00",
        "passed": "27 days, 22:14:51",
        "comments": null,
        "reporter": "brownj",
        "assignee": "melix",
        "reporter_is_assigned": false
    },
    "GROOVY-6525": {
        "created": "2014-01-17 07:07:21+00:00",
        "resolution": "2014-01-21 03:00:16+00:00",
        "passed": "3 days, 19:52:55",
        "comments": null,
        "reporter": "mperry",
        "assignee": "melix",
        "reporter_is_assigned": false
    },
    "GROOVY-6504": {
        "created": "2013-12-24 04:59:35+00:00",
        "resolution": "2014-01-20 09:12:06+00:00",
        "passed": "27 days, 4:12:31",
        "comments": null,
        "reporter": "melix",
        "assignee": "melix",
        "reporter_is_assigned": true
    },
    "GROOVY-6489": {
        "created": "2013-12-17 04:20:57+00:00",
        "resolution": "2014-01-22 10:14:07+00:00",
        "passed": "36 days, 5:53:10",
        "comments": null,
        "reporter": "cbrehm",
        "assignee": "melix",
        "reporter_is_assigned": false
    },
    "GROOVY-6480": {
        "created": "2013-12-11 08:46:25+00:00",
        "resolution": "2014-01-21 14:53:05+00:00",
        "passed": "41 days, 6:06:40",
        "comments": null,
        "reporter": "pledbrook",
        "assignee": "melix",
        "reporter_is_assigned": false
    },
    "GROOVY-6435": {
        "created": "2013-11-15 03:40:14+00:00",
        "resolution": "2013-11-18 05:55:40+00:00",
        "passed": "3 days, 2:15:26",
        "comments": null,
        "reporter": "mahool",
        "assignee": "blackdrag",
        "reporter_is_assigned": false
    },
    "GROOVY-6415": {
        "created": "2013-10-31 15:49:19+00:00",
        "resolution": "2014-04-30 13:53:27+00:00",
        "passed": "180 days, 22:04:08",
        "comments": null,
        "reporter": "acourtneybrown",
        "assignee": "blackdrag",
        "reporter_is_assigned": false
    },
    "GROOVY-6352": {
        "created": "2013-09-17 09:52:52+00:00",
        "resolution": "2015-12-22 10:53:24+00:00",
        "passed": "826 days, 1:00:32",
        "comments": null,
        "reporter": "blackdrag",
        "assignee": "pascalschumacher",
        "reporter_is_assigned": false
    },
    "GROOVY-6351": {
        "created": "2013-09-16 15:08:42+00:00",
        "resolution": "2016-10-06 22:51:49+00:00",
        "passed": "1116 days, 7:43:07",
        "comments": null,
        "reporter": "rcruzjo",
        "assignee": "",
        "reporter_is_assigned": false
    },
    "GROOVY-6350": {
        "created": "2013-09-16 09:58:12+00:00",
        "resolution": "2013-09-25 08:43:20+00:00",
        "passed": "8 days, 22:45:08",
        "comments": null,
        "reporter": "blackdrag",
        "assignee": "blackdrag",
        "reporter_is_assigned": true
    },
    "GROOVY-6349": {
        "created": "2013-09-16 09:18:22+00:00",
        "resolution": "2016-10-06 22:51:06+00:00",
        "passed": "1116 days, 13:32:44",
        "comments": null,
        "reporter": "rcruzjo",
        "assignee": "",
        "reporter_is_assigned": false
    },
    "GROOVY-6343": {
        "created": "2013-09-13 20:00:00+00:00",
        "resolution": "2014-05-15 13:26:20+00:00",
        "passed": "243 days, 17:26:20",
        "comments": null,
        "reporter": "eman",
        "assignee": "",
        "reporter_is_assigned": false
    },
    "GROOVY-6332": {
        "created": "2013-09-03 05:46:52+00:00",
        "resolution": "2013-09-10 11:43:16+00:00",
        "passed": "7 days, 5:56:24",
        "comments": null,
        "reporter": "pniederw",
        "assignee": "blackdrag",
        "reporter_is_assigned": false
    },
    "GROOVY-6325": {
        "created": "2013-08-27 21:35:09+00:00",
        "resolution": "2013-09-10 11:42:38+00:00",
        "passed": "13 days, 14:07:29",
        "comments": null,
        "reporter": "pniederw",
        "assignee": "blackdrag",
        "reporter_is_assigned": false
    },
    "GROOVY-6288": {
        "created": "2013-07-31 06:29:26+00:00",
        "resolution": "2013-08-26 07:33:09+00:00",
        "passed": "26 days, 1:03:43",
        "comments": null,
        "reporter": "egarcia",
        "assignee": "blackdrag",
        "reporter_is_assigned": false
    },
    "GROOVY-6241": {
        "created": "2013-07-08 05:04:29+00:00",
        "resolution": "2013-09-10 08:02:11+00:00",
        "passed": "64 days, 2:57:42",
        "comments": null,
        "reporter": "robfletcher",
        "assignee": "blackdrag",
        "reporter_is_assigned": false
    },
    "GROOVY-6238": {
        "created": "2013-07-04 11:14:15+00:00",
        "resolution": "2013-07-04 11:25:28+00:00",
        "passed": "0:11:13",
        "comments": null,
        "reporter": "melix",
        "assignee": "melix",
        "reporter_is_assigned": true
    },
    "GROOVY-6237": {
        "created": "2013-07-04 09:58:49+00:00",
        "resolution": "2013-07-08 08:19:40+00:00",
        "passed": "3 days, 22:20:51",
        "comments": null,
        "reporter": "blackdrag",
        "assignee": "blackdrag",
        "reporter_is_assigned": true
    },
    "GROOVY-6233": {
        "created": "2013-07-03 07:04:58+00:00",
        "resolution": "2013-07-08 08:18:45+00:00",
        "passed": "5 days, 1:13:47",
        "comments": null,
        "reporter": "blackdrag",
        "assignee": "blackdrag",
        "reporter_is_assigned": true
    },
    "GROOVY-6232": {
        "created": "2013-07-03 06:59:32+00:00",
        "resolution": "2013-07-08 08:18:26+00:00",
        "passed": "5 days, 1:18:54",
        "comments": null,
        "reporter": "blackdrag",
        "assignee": "blackdrag",
        "reporter_is_assigned": true
    },
    "GROOVY-6223": {
        "created": "2013-06-28 13:35:38+00:00",
        "resolution": "2013-07-01 05:13:12+00:00",
        "passed": "2 days, 15:37:34",
        "comments": null,
        "reporter": "mpierce",
        "assignee": "melix",
        "reporter_is_assigned": false
    },
    "GROOVY-6219": {
        "created": "2013-06-27 02:15:35+00:00",
        "resolution": "2013-06-27 07:08:53+00:00",
        "passed": "4:53:18",
        "comments": null,
        "reporter": "melix",
        "assignee": "melix",
        "reporter_is_assigned": true
    },
    "GROOVY-6218": {
        "created": "2013-06-27 02:13:12+00:00",
        "resolution": "2014-01-22 10:33:02+00:00",
        "passed": "209 days, 8:19:50",
        "comments": null,
        "reporter": "melix",
        "assignee": "melix",
        "reporter_is_assigned": true
    },
    "GROOVY-6207": {
        "created": "2013-06-12 13:45:10+00:00",
        "resolution": "2013-06-12 14:14:43+00:00",
        "passed": "0:29:33",
        "comments": null,
        "reporter": "melix",
        "assignee": "melix",
        "reporter_is_assigned": true
    },
    "GROOVY-6195": {
        "created": "2013-06-04 17:20:54+00:00",
        "resolution": "2013-06-07 11:01:44+00:00",
        "passed": "2 days, 17:40:50",
        "comments": null,
        "reporter": "bborchardt",
        "assignee": "melix",
        "reporter_is_assigned": false
    },
    "GROOVY-6180": {
        "created": "2013-05-28 07:57:12+00:00",
        "resolution": "2013-05-28 08:03:37+00:00",
        "passed": "0:06:25",
        "comments": null,
        "reporter": "melix",
        "assignee": "melix",
        "reporter_is_assigned": true
    },
    "GROOVY-6162": {
        "created": "2013-05-21 05:34:46+00:00",
        "resolution": "2013-05-29 03:35:06+00:00",
        "passed": "7 days, 22:00:20",
        "comments": null,
        "reporter": "pledbrook",
        "assignee": "melix",
        "reporter_is_assigned": false
    },
    "GROOVY-6129": {
        "created": "2013-04-30 10:06:29+00:00",
        "resolution": "2013-04-30 11:51:22+00:00",
        "passed": "1:44:53",
        "comments": null,
        "reporter": "Nkey",
        "assignee": "melix",
        "reporter_is_assigned": false
    },
    "GROOVY-6119": {
        "created": "2013-04-23 09:15:43+00:00",
        "resolution": "2013-04-25 02:43:24+00:00",
        "passed": "1 day, 17:27:41",
        "comments": null,
        "reporter": "melix",
        "assignee": "melix",
        "reporter_is_assigned": true
    },
    "GROOVY-6091": {
        "created": "2013-04-10 09:07:31+00:00",
        "resolution": "2013-04-10 09:31:48+00:00",
        "passed": "0:24:17",
        "comments": null,
        "reporter": "melix",
        "assignee": "melix",
        "reporter_is_assigned": true
    },
    "GROOVY-6086": {
        "created": "2013-04-07 23:11:32+00:00",
        "resolution": "2013-04-08 10:20:35+00:00",
        "passed": "11:09:03",
        "comments": null,
        "reporter": "lhotari",
        "assignee": "melix",
        "reporter_is_assigned": false
    },
    "GROOVY-6078": {
        "created": "2013-04-03 02:50:58+00:00",
        "resolution": "2013-04-03 15:19:15+00:00",
        "passed": "12:28:17",
        "comments": null,
        "reporter": "lhotari",
        "assignee": "melix",
        "reporter_is_assigned": false
    },
    "GROOVY-6051": {
        "created": "2013-03-13 17:00:31+00:00",
        "resolution": "2013-03-14 05:17:09+00:00",
        "passed": "12:16:38",
        "comments": null,
        "reporter": "oc",
        "assignee": "melix",
        "reporter_is_assigned": false
    },
    "GROOVY-6050": {
        "created": "2013-03-13 07:29:27+00:00",
        "resolution": "2013-03-13 08:10:24+00:00",
        "passed": "0:40:57",
        "comments": null,
        "reporter": "lhotari",
        "assignee": "melix",
        "reporter_is_assigned": false
    },
    "GROOVY-6047": {
        "created": "2013-03-12 08:53:26+00:00",
        "resolution": "2013-03-13 06:53:49+00:00",
        "passed": "22:00:23",
        "comments": null,
        "reporter": "oc",
        "assignee": "melix",
        "reporter_is_assigned": false
    },
    "GROOVY-6034": {
        "created": "2013-03-01 06:31:43+00:00",
        "resolution": "2013-03-06 05:35:11+00:00",
        "passed": "4 days, 23:03:28",
        "comments": null,
        "reporter": "mxm-groovy",
        "assignee": "melix",
        "reporter_is_assigned": false
    },
    "GROOVY-6030": {
        "created": "2013-02-27 14:12:17+00:00",
        "resolution": "2013-03-06 03:22:28+00:00",
        "passed": "6 days, 13:10:11",
        "comments": null,
        "reporter": "oc",
        "assignee": "melix",
        "reporter_is_assigned": false
    },
    "GROOVY-6021": {
        "created": "2013-02-25 07:19:09+00:00",
        "resolution": "2013-04-10 08:22:50+00:00",
        "passed": "44 days, 1:03:41",
        "comments": null,
        "reporter": "mxm-groovy",
        "assignee": "melix",
        "reporter_is_assigned": false
    },
    "GROOVY-6011": {
        "created": "2013-02-20 18:27:23+00:00",
        "resolution": "2013-03-05 01:46:59+00:00",
        "passed": "12 days, 7:19:36",
        "comments": null,
        "reporter": "werdna",
        "assignee": "melix",
        "reporter_is_assigned": false
    },
    "GROOVY-6000": {
        "created": "2013-02-14 02:47:16+00:00",
        "resolution": "2013-02-14 08:34:22+00:00",
        "passed": "5:47:06",
        "comments": null,
        "reporter": "pred",
        "assignee": "melix",
        "reporter_is_assigned": false
    },
    "GROOVY-5998": {
        "created": "2013-02-14 01:44:25+00:00",
        "resolution": "2014-05-15 15:47:32+00:00",
        "passed": "455 days, 14:03:07",
        "comments": null,
        "reporter": "pred",
        "assignee": "melix",
        "reporter_is_assigned": false
    },
    "GROOVY-5994": {
        "created": "2013-02-13 04:15:08+00:00",
        "resolution": "2013-02-13 10:05:07+00:00",
        "passed": "5:49:59",
        "comments": null,
        "reporter": "melix",
        "assignee": "melix",
        "reporter_is_assigned": true
    },
    "GROOVY-5991": {
        "created": "2013-02-12 13:51:57+00:00",
        "resolution": "2013-02-13 10:04:38+00:00",
        "passed": "20:12:41",
        "comments": null,
        "reporter": "oc",
        "assignee": "melix",
        "reporter_is_assigned": false
    },
    "GROOVY-5981": {
        "created": "2013-02-07 02:04:54+00:00",
        "resolution": "2014-05-15 13:56:28+00:00",
        "passed": "462 days, 11:51:34",
        "comments": null,
        "reporter": "rpodlas",
        "assignee": "blackdrag",
        "reporter_is_assigned": false
    },
    "GROOVY-5959": {
        "created": "2013-01-30 04:00:51+00:00",
        "resolution": "2013-02-07 03:31:45+00:00",
        "passed": "7 days, 23:30:54",
        "comments": null,
        "reporter": "pootow",
        "assignee": "melix",
        "reporter_is_assigned": false
    },
    "GROOVY-5910": {
        "created": "2013-01-15 04:40:25+00:00",
        "resolution": "2013-01-15 08:46:10+00:00",
        "passed": "4:05:45",
        "comments": null,
        "reporter": "guillaume",
        "assignee": "guillaume",
        "reporter_is_assigned": true
    },
    "GROOVY-5899": {
        "created": "2013-01-11 05:37:04+00:00",
        "resolution": "2014-01-15 11:14:46+00:00",
        "passed": "369 days, 5:37:42",
        "comments": null,
        "reporter": "cazacugmihai",
        "assignee": "melix",
        "reporter_is_assigned": false
    },
    "GROOVY-5885": {
        "created": "2013-01-07 01:00:47+00:00",
        "resolution": "2013-07-22 05:58:52+00:00",
        "passed": "196 days, 4:58:05",
        "comments": null,
        "reporter": "ddimitrov",
        "assignee": "blackdrag",
        "reporter_is_assigned": false
    },
    "GROOVY-5884": {
        "created": "2013-01-07 00:38:12+00:00",
        "resolution": "2013-01-09 10:46:54+00:00",
        "passed": "2 days, 10:08:42",
        "comments": null,
        "reporter": "ddimitrov",
        "assignee": "melix",
        "reporter_is_assigned": false
    },
    "GROOVY-5883": {
        "created": "2013-01-07 00:23:55+00:00",
        "resolution": "2013-07-22 05:02:13+00:00",
        "passed": "196 days, 4:38:18",
        "comments": null,
        "reporter": "ddimitrov",
        "assignee": "blackdrag",
        "reporter_is_assigned": false
    },
    "GROOVY-5880": {
        "created": "2013-01-06 23:45:19+00:00",
        "resolution": "2013-02-11 09:06:53+00:00",
        "passed": "35 days, 9:21:34",
        "comments": null,
        "reporter": "ddimitrov",
        "assignee": "melix",
        "reporter_is_assigned": false
    },
    "GROOVY-5873": {
        "created": "2013-01-02 08:20:49+00:00",
        "resolution": "2013-07-19 13:52:57+00:00",
        "passed": "198 days, 5:32:08",
        "comments": null,
        "reporter": "djh",
        "assignee": "blackdrag",
        "reporter_is_assigned": false
    },
    "GROOVY-5872": {
        "created": "2013-01-02 02:12:40+00:00",
        "resolution": "2013-01-07 06:22:16+00:00",
        "passed": "5 days, 4:09:36",
        "comments": null,
        "reporter": "uehaj",
        "assignee": "melix",
        "reporter_is_assigned": false
    },
    "GROOVY-5870": {
        "created": "2013-01-01 08:55:28+00:00",
        "resolution": "2013-01-09 11:39:56+00:00",
        "passed": "8 days, 2:44:28",
        "comments": null,
        "reporter": "betak102",
        "assignee": "melix",
        "reporter_is_assigned": false
    },
    "GROOVY-5850": {
        "created": "2012-12-17 17:39:08+00:00",
        "resolution": "2013-01-27 07:05:56+00:00",
        "passed": "40 days, 13:26:48",
        "comments": null,
        "reporter": "adriannistor",
        "assignee": "pschumacher",
        "reporter_is_assigned": false
    },
    "GROOVY-5839": {
        "created": "2012-12-05 08:32:49+00:00",
        "resolution": "2013-07-19 08:41:46+00:00",
        "passed": "226 days, 0:08:57",
        "comments": null,
        "reporter": "ddimitrov",
        "assignee": "blackdrag",
        "reporter_is_assigned": false
    },
    "GROOVY-5834": {
        "created": "2012-12-02 20:27:24+00:00",
        "resolution": "2012-12-03 04:28:17+00:00",
        "passed": "8:00:53",
        "comments": null,
        "reporter": "ddimitrov",
        "assignee": "melix",
        "reporter_is_assigned": false
    },
    "GROOVY-5779": {
        "created": "2012-11-02 05:41:07+00:00",
        "resolution": "2012-11-02 10:24:38+00:00",
        "passed": "4:43:31",
        "comments": null,
        "reporter": "lvanek",
        "assignee": "melix",
        "reporter_is_assigned": false
    },
    "GROOVY-5770": {
        "created": "2012-10-26 08:27:36+00:00",
        "resolution": "2015-03-20 09:10:26+00:00",
        "passed": "875 days, 0:42:50",
        "comments": null,
        "reporter": "carlosapc",
        "assignee": "melix",
        "reporter_is_assigned": false
    },
    "GROOVY-5753": {
        "created": "2012-10-11 05:28:15+00:00",
        "resolution": "2012-11-21 01:50:03+00:00",
        "passed": "40 days, 20:21:48",
        "comments": null,
        "reporter": "perplex79",
        "assignee": "melix",
        "reporter_is_assigned": false
    },
    "GROOVY-5748": {
        "created": "2012-10-08 14:49:41+00:00",
        "resolution": "2012-10-10 09:14:28+00:00",
        "passed": "1 day, 18:24:47",
        "comments": null,
        "reporter": "paulk",
        "assignee": "melix",
        "reporter_is_assigned": false
    },
    "GROOVY-5743": {
        "created": "2012-10-04 11:11:55+00:00",
        "resolution": "2012-11-20 04:49:30+00:00",
        "passed": "46 days, 17:37:35",
        "comments": null,
        "reporter": "tim_yates",
        "assignee": "melix",
        "reporter_is_assigned": false
    },
    "GROOVY-5742": {
        "created": "2012-10-03 21:51:38+00:00",
        "resolution": "2013-07-16 08:34:12+00:00",
        "passed": "285 days, 10:42:34",
        "comments": null,
        "reporter": "paulk",
        "assignee": "blackdrag",
        "reporter_is_assigned": false
    },
    "GROOVY-5735": {
        "created": "2012-10-01 09:17:57+00:00",
        "resolution": "2012-11-23 09:43:20+00:00",
        "passed": "53 days, 0:25:23",
        "comments": null,
        "reporter": "rcruzjo",
        "assignee": "melix",
        "reporter_is_assigned": false
    },
    "GROOVY-5724": {
        "created": "2012-09-25 02:55:00+00:00",
        "resolution": "2012-11-26 07:34:18+00:00",
        "passed": "62 days, 4:39:18",
        "comments": null,
        "reporter": "peti",
        "assignee": "melix",
        "reporter_is_assigned": false
    },
    "GROOVY-5720": {
        "created": "2012-09-21 06:46:40+00:00",
        "resolution": "2012-11-22 06:20:40+00:00",
        "passed": "61 days, 23:34:00",
        "comments": null,
        "reporter": "fplass",
        "assignee": "melix",
        "reporter_is_assigned": false
    },
    "GROOVY-5712": {
        "created": "2012-09-19 03:06:41+00:00",
        "resolution": "2012-11-22 02:21:10+00:00",
        "passed": "63 days, 23:14:29",
        "comments": null,
        "reporter": "peti",
        "assignee": "melix",
        "reporter_is_assigned": false
    },
    "GROOVY-5707": {
        "created": "2012-09-14 08:30:23+00:00",
        "resolution": "2012-09-14 08:33:31+00:00",
        "passed": "0:03:08",
        "comments": null,
        "reporter": "melix",
        "assignee": "melix",
        "reporter_is_assigned": true
    },
    "GROOVY-5705": {
        "created": "2012-09-12 05:21:42+00:00",
        "resolution": "2012-09-13 10:22:59+00:00",
        "passed": "1 day, 5:01:17",
        "comments": null,
        "reporter": "guillaume",
        "assignee": "guillaume",
        "reporter_is_assigned": true
    },
    "GROOVY-5702": {
        "created": "2012-09-11 09:34:38+00:00",
        "resolution": "2012-09-13 09:57:01+00:00",
        "passed": "2 days, 0:22:23",
        "comments": null,
        "reporter": "guillaume",
        "assignee": "melix",
        "reporter_is_assigned": false
    },
    "GROOVY-5700": {
        "created": "2012-09-11 04:38:52+00:00",
        "resolution": "2012-09-12 07:13:52+00:00",
        "passed": "1 day, 2:35:00",
        "comments": null,
        "reporter": "guillaume",
        "assignee": "melix",
        "reporter_is_assigned": false
    },
    "GROOVY-5699": {
        "created": "2012-09-11 04:18:02+00:00",
        "resolution": "2012-09-11 12:24:13+00:00",
        "passed": "8:06:11",
        "comments": null,
        "reporter": "guillaume",
        "assignee": "melix",
        "reporter_is_assigned": false
    },
    "GROOVY-5698": {
        "created": "2012-09-11 03:32:29+00:00",
        "resolution": "2012-09-13 05:05:54+00:00",
        "passed": "2 days, 1:33:25",
        "comments": null,
        "reporter": "guillaume",
        "assignee": "melix",
        "reporter_is_assigned": false
    },
    "GROOVY-5653": {
        "created": "2012-08-01 16:11:21+00:00",
        "resolution": "2012-08-29 09:08:43+00:00",
        "passed": "27 days, 16:57:22",
        "comments": null,
        "reporter": "guillaume",
        "assignee": "melix",
        "reporter_is_assigned": false
    },
    "GROOVY-5650": {
        "created": "2012-08-01 02:38:53+00:00",
        "resolution": "2012-08-22 07:43:20+00:00",
        "passed": "21 days, 5:04:27",
        "comments": null,
        "reporter": "perplex79",
        "assignee": "melix",
        "reporter_is_assigned": false
    },
    "GROOVY-5644": {
        "created": "2012-07-29 02:39:29+00:00",
        "resolution": "2012-08-21 09:27:45+00:00",
        "passed": "23 days, 6:48:16",
        "comments": null,
        "reporter": "uehaj",
        "assignee": "melix",
        "reporter_is_assigned": false
    },
    "GROOVY-5640": {
        "created": "2012-07-28 08:05:56+00:00",
        "resolution": "2012-08-27 09:38:52+00:00",
        "passed": "30 days, 1:32:56",
        "comments": null,
        "reporter": "wujek.srujek",
        "assignee": "melix",
        "reporter_is_assigned": false
    },
    "GROOVY-5639": {
        "created": "2012-07-27 17:16:18+00:00",
        "resolution": "2012-08-21 11:07:41+00:00",
        "passed": "24 days, 17:51:23",
        "comments": null,
        "reporter": "mpierce",
        "assignee": "melix",
        "reporter_is_assigned": false
    },
    "GROOVY-5622": {
        "created": "2012-07-24 00:06:02+00:00",
        "resolution": "2012-07-24 02:48:38+00:00",
        "passed": "2:42:36",
        "comments": null,
        "reporter": "nplekhanov",
        "assignee": "melix",
        "reporter_is_assigned": false
    },
    "GROOVY-5618": {
        "created": "2012-07-20 10:53:44+00:00",
        "resolution": "2012-07-24 02:51:05+00:00",
        "passed": "3 days, 15:57:21",
        "comments": null,
        "reporter": "melix",
        "assignee": "melix",
        "reporter_is_assigned": true
    },
    "GROOVY-5617": {
        "created": "2012-07-20 04:39:17+00:00",
        "resolution": "2012-07-20 07:46:52+00:00",
        "passed": "3:07:35",
        "comments": null,
        "reporter": "paulk",
        "assignee": "melix",
        "reporter_is_assigned": false
    },
    "GROOVY-5615": {
        "created": "2012-07-19 09:18:18+00:00",
        "resolution": "2012-07-19 11:27:03+00:00",
        "passed": "2:08:45",
        "comments": null,
        "reporter": "ariel.andres.morelli",
        "assignee": "melix",
        "reporter_is_assigned": false
    },
    "GROOVY-5614": {
        "created": "2012-07-19 08:07:31+00:00",
        "resolution": "2012-07-20 07:44:31+00:00",
        "passed": "23:37:00",
        "comments": null,
        "reporter": "richardwarburton",
        "assignee": "melix",
        "reporter_is_assigned": false
    },
    "GROOVY-5611": {
        "created": "2012-07-18 04:51:49+00:00",
        "resolution": "2012-07-18 07:18:38+00:00",
        "passed": "2:26:49",
        "comments": null,
        "reporter": "melix",
        "assignee": "melix",
        "reporter_is_assigned": true
    },
    "GROOVY-5610": {
        "created": "2012-07-17 14:41:37+00:00",
        "resolution": "2013-07-16 10:12:54+00:00",
        "passed": "363 days, 19:31:17",
        "comments": null,
        "reporter": "melix",
        "assignee": "blackdrag",
        "reporter_is_assigned": false
    },
    "GROOVY-5601": {
        "created": "2012-07-14 06:27:40+00:00",
        "resolution": "2012-07-16 03:47:51+00:00",
        "passed": "1 day, 21:20:11",
        "comments": null,
        "reporter": "wujek.srujek",
        "assignee": "melix",
        "reporter_is_assigned": false
    },
    "GROOVY-5595": {
        "created": "2012-07-12 04:52:19+00:00",
        "resolution": "2012-07-12 06:55:49+00:00",
        "passed": "2:03:30",
        "comments": null,
        "reporter": "melix",
        "assignee": "melix",
        "reporter_is_assigned": true
    },
    "GROOVY-5594": {
        "created": "2012-07-12 04:31:43+00:00",
        "resolution": "2012-07-12 06:55:36+00:00",
        "passed": "2:23:53",
        "comments": null,
        "reporter": "melix",
        "assignee": "melix",
        "reporter_is_assigned": true
    },
    "GROOVY-5589": {
        "created": "2012-07-11 11:25:30+00:00",
        "resolution": "2012-07-11 11:45:09+00:00",
        "passed": "0:19:39",
        "comments": null,
        "reporter": "melix",
        "assignee": "melix",
        "reporter_is_assigned": true
    },
    "GROOVY-5580": {
        "created": "2012-07-06 20:54:38+00:00",
        "resolution": "2012-07-09 10:24:44+00:00",
        "passed": "2 days, 13:30:06",
        "comments": null,
        "reporter": "scoreunder",
        "assignee": "melix",
        "reporter_is_assigned": false
    },
    "GROOVY-5578": {
        "created": "2012-07-06 07:19:37+00:00",
        "resolution": "2012-07-09 11:52:40+00:00",
        "passed": "3 days, 4:33:03",
        "comments": null,
        "reporter": "graemerocher",
        "assignee": "melix",
        "reporter_is_assigned": false
    },
    "GROOVY-5573": {
        "created": "2012-07-03 07:36:24+00:00",
        "resolution": "2012-07-05 14:43:50+00:00",
        "passed": "2 days, 7:07:26",
        "comments": null,
        "reporter": "graemerocher",
        "assignee": "melix",
        "reporter_is_assigned": false
    },
    "GROOVY-5569": {
        "created": "2012-07-02 07:39:31+00:00",
        "resolution": "2012-07-12 11:48:00+00:00",
        "passed": "10 days, 4:08:29",
        "comments": null,
        "reporter": "graemerocher",
        "assignee": "melix",
        "reporter_is_assigned": false
    },
    "GROOVY-5559": {
        "created": "2012-06-29 08:44:03+00:00",
        "resolution": "2012-07-20 07:47:41+00:00",
        "passed": "20 days, 23:03:38",
        "comments": null,
        "reporter": "graemerocher",
        "assignee": "melix",
        "reporter_is_assigned": false
    },
    "GROOVY-5532": {
        "created": "2012-06-19 13:37:20+00:00",
        "resolution": "2012-06-20 04:44:36+00:00",
        "passed": "15:07:16",
        "comments": null,
        "reporter": "guillaume",
        "assignee": "melix",
        "reporter_is_assigned": false
    },
    "GROOVY-5530": {
        "created": "2012-06-19 12:47:40+00:00",
        "resolution": "2012-06-20 09:37:49+00:00",
        "passed": "20:50:09",
        "comments": null,
        "reporter": "guillaume",
        "assignee": "melix",
        "reporter_is_assigned": false
    },
    "GROOVY-5528": {
        "created": "2012-06-19 06:43:19+00:00",
        "resolution": "2012-06-19 09:39:47+00:00",
        "passed": "2:56:28",
        "comments": null,
        "reporter": "blackdrag",
        "assignee": "melix",
        "reporter_is_assigned": false
    },
    "GROOVY-5522": {
        "created": "2012-06-14 09:25:49+00:00",
        "resolution": "2012-06-19 08:05:36+00:00",
        "passed": "4 days, 22:39:47",
        "comments": null,
        "reporter": "graemerocher",
        "assignee": "melix",
        "reporter_is_assigned": false
    },
    "GROOVY-5521": {
        "created": "2012-06-14 09:08:25+00:00",
        "resolution": "2012-06-18 08:10:24+00:00",
        "passed": "3 days, 23:01:59",
        "comments": null,
        "reporter": "graemerocher",
        "assignee": "melix",
        "reporter_is_assigned": false
    },
    "GROOVY-5520": {
        "created": "2012-06-14 09:00:32+00:00",
        "resolution": "2012-06-18 04:32:13+00:00",
        "passed": "3 days, 19:31:41",
        "comments": null,
        "reporter": "graemerocher",
        "assignee": "melix",
        "reporter_is_assigned": false
    },
    "GROOVY-5519": {
        "created": "2012-06-14 08:22:05+00:00",
        "resolution": "2012-06-18 07:25:04+00:00",
        "passed": "3 days, 23:02:59",
        "comments": null,
        "reporter": "graemerocher",
        "assignee": "melix",
        "reporter_is_assigned": false
    },
    "GROOVY-5516": {
        "created": "2012-06-14 03:50:30+00:00",
        "resolution": "2012-06-14 04:07:22+00:00",
        "passed": "0:16:52",
        "comments": null,
        "reporter": "melix",
        "assignee": "melix",
        "reporter_is_assigned": true
    },
    "GROOVY-5498": {
        "created": "2012-06-05 13:19:13+00:00",
        "resolution": "2012-06-11 07:07:33+00:00",
        "passed": "5 days, 17:48:20",
        "comments": null,
        "reporter": "ariel.andres.morelli",
        "assignee": "melix",
        "reporter_is_assigned": false
    },
    "GROOVY-5497": {
        "created": "2012-06-05 13:14:54+00:00",
        "resolution": "2012-06-11 04:35:40+00:00",
        "passed": "5 days, 15:20:46",
        "comments": null,
        "reporter": "ariel.andres.morelli",
        "assignee": "melix",
        "reporter_is_assigned": false
    },
    "GROOVY-5482": {
        "created": "2012-05-31 05:46:11+00:00",
        "resolution": "2012-06-12 12:35:35+00:00",
        "passed": "12 days, 6:49:24",
        "comments": null,
        "reporter": "rgarcia",
        "assignee": "melix",
        "reporter_is_assigned": false
    },
    "GROOVY-5480": {
        "created": "2012-05-31 04:05:30+00:00",
        "resolution": "2012-06-12 08:25:25+00:00",
        "passed": "12 days, 4:19:55",
        "comments": null,
        "reporter": "rgarcia",
        "assignee": "melix",
        "reporter_is_assigned": false
    },
    "GROOVY-5470": {
        "created": "2012-05-24 02:47:13+00:00",
        "resolution": "2012-06-12 15:21:50+00:00",
        "passed": "19 days, 12:34:37",
        "comments": null,
        "reporter": "rgarcia",
        "assignee": "melix",
        "reporter_is_assigned": false
    },
    "GROOVY-5456": {
        "created": "2012-05-16 18:09:52+00:00",
        "resolution": "2012-06-12 14:07:50+00:00",
        "passed": "26 days, 19:57:58",
        "comments": null,
        "reporter": "rgarcia",
        "assignee": "melix",
        "reporter_is_assigned": false
    },
    "GROOVY-5454": {
        "created": "2012-05-16 07:21:28+00:00",
        "resolution": "2012-05-18 02:24:07+00:00",
        "passed": "1 day, 19:02:39",
        "comments": null,
        "reporter": "melix",
        "assignee": "melix",
        "reporter_is_assigned": true
    },
    "GROOVY-5443": {
        "created": "2012-05-08 16:33:06+00:00",
        "resolution": "2012-05-09 04:14:20+00:00",
        "passed": "11:41:14",
        "comments": null,
        "reporter": "rgarcia",
        "assignee": "melix",
        "reporter_is_assigned": false
    },
    "GROOVY-5415": {
        "created": "2012-04-21 18:53:31+00:00",
        "resolution": "2012-05-02 09:45:43+00:00",
        "passed": "10 days, 14:52:12",
        "comments": null,
        "reporter": "mmrath",
        "assignee": "melix",
        "reporter_is_assigned": false
    },
    "GROOVY-5411": {
        "created": "2012-04-17 14:43:24+00:00",
        "resolution": "2012-04-26 11:08:03+00:00",
        "passed": "8 days, 20:24:39",
        "comments": null,
        "reporter": "aclement",
        "assignee": "melix",
        "reporter_is_assigned": false
    },
    "GROOVY-5332": {
        "created": "2012-02-27 06:50:58+00:00",
        "resolution": "2012-02-27 06:51:57+00:00",
        "passed": "0:00:59",
        "comments": null,
        "reporter": "melix",
        "assignee": "melix",
        "reporter_is_assigned": true
    },
    "GROOVY-5295": {
        "created": "2012-02-10 10:48:53+00:00",
        "resolution": "2012-02-10 10:51:08+00:00",
        "passed": "0:02:15",
        "comments": null,
        "reporter": "melix",
        "assignee": "melix",
        "reporter_is_assigned": true
    },
    "GROOVY-5240": {
        "created": "2012-01-06 09:46:06+00:00",
        "resolution": "2012-01-09 10:53:08+00:00",
        "passed": "3 days, 1:07:02",
        "comments": null,
        "reporter": "guillaume",
        "assignee": "melix",
        "reporter_is_assigned": false
    },
    "GROOVY-5238": {
        "created": "2012-01-06 06:02:32+00:00",
        "resolution": "2012-01-06 08:13:47+00:00",
        "passed": "2:11:15",
        "comments": null,
        "reporter": "melix",
        "assignee": "melix",
        "reporter_is_assigned": true
    },
    "GROOVY-5237": {
        "created": "2012-01-06 05:42:21+00:00",
        "resolution": "2012-01-06 08:00:00+00:00",
        "passed": "2:17:39",
        "comments": null,
        "reporter": "guillaume",
        "assignee": "melix",
        "reporter_is_assigned": false
    },
    "GROOVY-5235": {
        "created": "2012-01-05 14:34:16+00:00",
        "resolution": "2012-02-17 03:57:09+00:00",
        "passed": "42 days, 13:22:53",
        "comments": null,
        "reporter": "melix",
        "assignee": "melix",
        "reporter_is_assigned": true
    },
    "GROOVY-5233": {
        "created": "2012-01-05 12:05:43+00:00",
        "resolution": "2012-01-09 10:52:50+00:00",
        "passed": "3 days, 22:47:07",
        "comments": null,
        "reporter": "guillaume",
        "assignee": "melix",
        "reporter_is_assigned": false
    },
    "GROOVY-5232": {
        "created": "2012-01-05 09:43:26+00:00",
        "resolution": "2012-01-06 08:42:17+00:00",
        "passed": "22:58:51",
        "comments": null,
        "reporter": "guillaume",
        "assignee": "melix",
        "reporter_is_assigned": false
    },
    "GROOVY-5231": {
        "created": "2012-01-05 09:22:34+00:00",
        "resolution": "2012-01-05 14:36:41+00:00",
        "passed": "5:14:07",
        "comments": null,
        "reporter": "guillaume",
        "assignee": "melix",
        "reporter_is_assigned": false
    },
    "GROOVY-5229": {
        "created": "2012-01-04 16:10:43+00:00",
        "resolution": "2012-01-04 16:12:46+00:00",
        "passed": "0:02:03",
        "comments": null,
        "reporter": "melix",
        "assignee": "melix",
        "reporter_is_assigned": true
    },
    "GROOVY-5228": {
        "created": "2012-01-04 10:36:52+00:00",
        "resolution": "2012-01-04 10:39:22+00:00",
        "passed": "0:02:30",
        "comments": null,
        "reporter": "melix",
        "assignee": "melix",
        "reporter_is_assigned": true
    },
    "GROOVY-5226": {
        "created": "2012-01-03 12:27:54+00:00",
        "resolution": "2012-01-03 12:34:50+00:00",
        "passed": "0:06:56",
        "comments": null,
        "reporter": "melix",
        "assignee": "melix",
        "reporter_is_assigned": true
    },
    "GROOVY-5222": {
        "created": "2011-12-29 10:21:12+00:00",
        "resolution": "2011-12-29 10:21:18+00:00",
        "passed": "0:00:06",
        "comments": null,
        "reporter": "melix",
        "assignee": "melix",
        "reporter_is_assigned": true
    },
    "GROOVY-5217": {
        "created": "2011-12-27 12:01:21+00:00",
        "resolution": "2011-12-27 12:13:06+00:00",
        "passed": "0:11:45",
        "comments": null,
        "reporter": "melix",
        "assignee": "melix",
        "reporter_is_assigned": true
    },
    "GROOVY-5213": {
        "created": "2011-12-26 10:30:26+00:00",
        "resolution": "2011-12-26 10:32:03+00:00",
        "passed": "0:01:37",
        "comments": null,
        "reporter": "melix",
        "assignee": "melix",
        "reporter_is_assigned": true
    },
    "GROOVY-5184": {
        "created": "2011-12-12 03:25:40+00:00",
        "resolution": "2011-12-12 08:00:54+00:00",
        "passed": "4:35:14",
        "comments": null,
        "reporter": "melix",
        "assignee": "melix",
        "reporter_is_assigned": true
    },
    "GROOVY-5178": {
        "created": "2011-12-08 07:36:24+00:00",
        "resolution": "2011-12-09 11:14:30+00:00",
        "passed": "1 day, 3:38:06",
        "comments": null,
        "reporter": "vns",
        "assignee": "melix",
        "reporter_is_assigned": false
    },
    "GROOVY-5177": {
        "created": "2011-12-08 07:34:25+00:00",
        "resolution": "2011-12-08 08:35:06+00:00",
        "passed": "1:00:41",
        "comments": null,
        "reporter": "vns",
        "assignee": "melix",
        "reporter_is_assigned": false
    },
    "GROOVY-5175": {
        "created": "2011-12-08 06:07:18+00:00",
        "resolution": "2011-12-08 08:58:50+00:00",
        "passed": "2:51:32",
        "comments": null,
        "reporter": "vns",
        "assignee": "melix",
        "reporter_is_assigned": false
    },
    "GROOVY-5172": {
        "created": "2011-12-06 08:59:03+00:00",
        "resolution": "2011-12-06 09:00:16+00:00",
        "passed": "0:01:13",
        "comments": null,
        "reporter": "melix",
        "assignee": "melix",
        "reporter_is_assigned": true
    },
    "GROOVY-5171": {
        "created": "2011-12-06 04:32:20+00:00",
        "resolution": "2011-12-06 04:40:52+00:00",
        "passed": "0:08:32",
        "comments": null,
        "reporter": "melix",
        "assignee": "melix",
        "reporter_is_assigned": true
    },
    "GROOVY-5168": {
        "created": "2011-12-05 09:43:39+00:00",
        "resolution": "2011-12-05 10:41:36+00:00",
        "passed": "0:57:57",
        "comments": null,
        "reporter": "guillaume",
        "assignee": "melix",
        "reporter_is_assigned": false
    },
    "GROOVY-5167": {
        "created": "2011-12-05 09:36:58+00:00",
        "resolution": "2011-12-05 10:09:48+00:00",
        "passed": "0:32:50",
        "comments": null,
        "reporter": "guillaume",
        "assignee": "melix",
        "reporter_is_assigned": false
    },
    "GROOVY-5166": {
        "created": "2011-12-05 06:54:29+00:00",
        "resolution": "2011-12-05 10:55:09+00:00",
        "passed": "4:00:40",
        "comments": null,
        "reporter": "melix",
        "assignee": "melix",
        "reporter_is_assigned": true
    },
    "GROOVY-5160": {
        "created": "2011-12-02 08:49:20+00:00",
        "resolution": "2011-12-02 09:46:26+00:00",
        "passed": "0:57:06",
        "comments": null,
        "reporter": "melix",
        "assignee": "melix",
        "reporter_is_assigned": true
    },
    "GROOVY-5148": {
        "created": "2011-11-25 11:52:01+00:00",
        "resolution": "2011-11-25 12:49:40+00:00",
        "passed": "0:57:39",
        "comments": null,
        "reporter": "melix",
        "assignee": "melix",
        "reporter_is_assigned": true
    },
    "GROOVY-5147": {
        "created": "2011-11-25 11:50:38+00:00",
        "resolution": "2011-11-25 12:49:48+00:00",
        "passed": "0:59:10",
        "comments": null,
        "reporter": "melix",
        "assignee": "melix",
        "reporter_is_assigned": true
    },
    "GROOVY-5145": {
        "created": "2011-11-24 09:59:07+00:00",
        "resolution": "2011-11-24 10:05:18+00:00",
        "passed": "0:06:11",
        "comments": null,
        "reporter": "melix",
        "assignee": "melix",
        "reporter_is_assigned": true
    },
    "GROOVY-5141": {
        "created": "2011-11-24 05:48:47+00:00",
        "resolution": "2011-11-24 05:51:52+00:00",
        "passed": "0:03:05",
        "comments": null,
        "reporter": "melix",
        "assignee": "melix",
        "reporter_is_assigned": true
    },
    "GROOVY-5127": {
        "created": "2011-11-15 10:47:38+00:00",
        "resolution": "2011-11-29 04:42:49+00:00",
        "passed": "13 days, 17:55:11",
        "comments": null,
        "reporter": "melix",
        "assignee": "melix",
        "reporter_is_assigned": true
    },
    "GROOVY-5126": {
        "created": "2011-11-15 10:14:29+00:00",
        "resolution": "2011-11-29 04:42:22+00:00",
        "passed": "13 days, 18:27:53",
        "comments": null,
        "reporter": "melix",
        "assignee": "melix",
        "reporter_is_assigned": true
    }
}